plot_context_manager/__init__.py
plot_context_manager/plot.py
plot_context_manager/plot_manager.py
plot_context_manager/style_setter.py
plot_context_manager-0.0.1.dist-info/LICENSE
plot_context_manager-0.0.1.dist-info/METADATA
plot_context_manager-0.0.1.dist-info/WHEEL
plot_context_manager-0.0.1.dist-info/top_level.txt
plot_context_manager-0.0.1.dist-info/RECORD
