Metadata-Version: 2.1
Name: plot-context-manager
Version: 0.0.1
Summary: The package to work with plots as with context managers.
Home-page: https://github.com/AlbertFarkhutdinov/plot_context_manager
Author: Albert Farkhutdinov
Author-email: albertfarhutdinov@gmail.com
Classifier: Development Status :: 3 - Alpha
Classifier: Programming Language :: Python :: 3.11
Classifier: License :: OSI Approved :: MIT License
Classifier: Operating System :: OS Independent
Requires-Python: >=3.9
License-File: LICENSE
Requires-Dist: matplotlib (<4,>3)
